psenv/__init__.py
psenv/__main__.py
psenv/aws/__init__.py
psenv/aws/parameter_store.py
psenv/aws/sts.py
psenv/cli/__init__.py
psenv/cli/exec.py
psenv/cli/get.py
psenv/cli/init.py
psenv/cli/inject.py
psenv/cli/put.py
psenv/core/command.py
psenv/core/config.py
psenv/core/context.py
psenv/core/diff.py
psenv/core/fileio.py
psenv/core/models.py
psenv/core/paths.py
psenv/core/synchronizer.py
psenv/error_handling/__init__.py
psenv/error_handling/exceptions.py
psenv/templates/psenv.template.yml
pytoolbelt_psenv-0.21.0.dist-info/licenses/LICENSE
pytoolbelt_psenv-0.21.0.dist-info/METADATA
pytoolbelt_psenv-0.21.0.dist-info/WHEEL
pytoolbelt_psenv-0.21.0.dist-info/entry_points.txt
pytoolbelt_psenv-0.21.0.dist-info/top_level.txt
pytoolbelt_psenv-0.21.0.dist-info/RECORD
