Metadata-Version: 2.4
Name: pytoolbelt-psenv
Version: 0.21.0
Summary: A tool for managing AWS Parameter Store environments
Requires-Python: >=3.10
License-File: LICENSE
Requires-Dist: python-dotenv==1.1.0
Requires-Dist: pyyaml==6.0.2
Requires-Dist: boto3==1.38.32
Requires-Dist: structlog==25.4.0
Requires-Dist: pydantic==2.11.5
Requires-Dist: boto3-stubs[ssm,sts]==1.38.32
Provides-Extra: dev
Requires-Dist: pytest==8.4.0; extra == "dev"
Requires-Dist: pytest-cov==6.1.1; extra == "dev"
Requires-Dist: ruff==0.11.13; extra == "dev"
Requires-Dist: boto3-stubs[ssm,sts]==1.38.32; extra == "dev"
Requires-Dist: mkdocs==1.6.0; extra == "dev"
Requires-Dist: mkdocs-material==9.5.26; extra == "dev"
Dynamic: license-file
